ai_clients/__init__.py
ai_clients/py.typed
ai_clients/base/__init__.py
ai_clients/base/client.py
ai_clients/base/errors.py
ai_clients/base/types.py
ai_clients/codestral/__init__.py
ai_clients/codestral/client.py
ai_clients/codestral/types.py
ai_clients-0.2.0.dist-info/METADATA
ai_clients-0.2.0.dist-info/WHEEL
ai_clients-0.2.0.dist-info/licenses/LICENSE
ai_clients-0.2.0.dist-info/RECORD
