Metadata-Version: 2.4
Name: ai-clients
Version: 0.2.0
Summary: HTTP clients for easy integration with different ai models
Project-URL: Repository, https://github.com/Vladimir-Titov/ai-clients
Project-URL: Issues, https://github.com/Vladimir-Titov/ai-clients/issues
Author-email: vtitov <v.v.titov94@gmail.com>
License-File: LICENSE
Classifier: Development Status :: 5 - Production/Stable
Classifier: Programming Language :: Python :: 3.10
Classifier: Programming Language :: Python :: 3.11
Classifier: Programming Language :: Python :: 3.12
Classifier: Typing :: Typed
Requires-Python: >=3.10
Requires-Dist: aiohttp>=3.11.12
Requires-Dist: pydantic>=2.10.6
Requires-Dist: ujson>=5.10.0
